deba/__init__.py
deba/__main__.py
deba/attrs_utils.py
deba/attrs_utils_test.py
deba/config.py
deba/serialize.py
deba/serialize_test.py
deba/test_utils.py
deba/commands/Makefile
deba/commands/__init__.py
deba/commands/ast.py
deba/commands/data_dir.py
deba/commands/data_dir_test.py
deba/commands/debug.py
deba/commands/decorators.py
deba/commands/decorators_test.py
deba/commands/deps.py
deba/commands/deps_test.py
deba/commands/init.py
deba/commands/md5_dir.py
deba/commands/md5_dir_test.py
deba/commands/python_path.py
deba/commands/stages.py
deba/commands/stages_test.py
deba/commands/targets.py
deba/commands/targets_test.py
deba/commands/test.py
deba/commands/test_test.py
deba/deps/__init__.py
deba/deps/expr.py
deba/deps/expr_test.py
deba/deps/find.py
deba/deps/find_test.py
deba/deps/module.py
deba-0.1.8.dist-info/LICENSE
deba-0.1.8.dist-info/METADATA
deba-0.1.8.dist-info/WHEEL
deba-0.1.8.dist-info/entry_points.txt
deba-0.1.8.dist-info/top_level.txt
deba-0.1.8.dist-info/RECORD
