Metadata-Version: 2.1
Name: deba
Version: 0.1.8
Summary: data pipeline framework with auto dependency discovery
Home-page: https://github.com/pckhoi/deba
Author: Khoi Pham
Author-email: pckhoi@gmail.com
Project-URL: Bug Tracker, https://github.com/pckhoi/deba/issues
Classifier: Programming Language :: Python :: 3
Classifier: License :: OSI Approved :: MIT License
Classifier: Operating System :: OS Independent
Requires-Python: >=3.8
License-File: LICENSE
Requires-Dist: attrs (>=21.4.0)
Requires-Dist: zope.interface (>=5.4.0)
Requires-Dist: PyYAML (>=5.3)
Requires-Dist: astpretty (>=3.0.0)
